setup.py
breach_buster/__init__.py
breach_buster/demo_server.py
breach_buster.egg-info/PKG-INFO
breach_buster.egg-info/SOURCES.txt
breach_buster.egg-info/dependency_links.txt
breach_buster.egg-info/requires.txt
breach_buster.egg-info/top_level.txt
breach_buster.egg-info/zip-safe
breach_buster/examples/__init__.py
breach_buster/examples/demo_server.py
breach_buster/middleware/__init__.py
breach_buster/middleware/gzip.py