Metadata-Version: 1.0
Name: breach-buster
Version: 0.0.4
Summary: BREACH resistant gzip middleware for Django
Home-page: https://github.com/wnyc/breach_buster
Author: Adam DePrince
Author-email: adeprince@nypublicradio.org
License: GPLv3
Platform: UNKNOWN
